setup.py
jcore_api/__init__.py
jcore_api/_api.py
jcore_api/_api_common.py
jcore_api/_connection.py
jcore_api/_jcore_web_socket.py
jcore_api/_protocol.py
jcore_api/exceptions.py
jcore_api.egg-info/PKG-INFO
jcore_api.egg-info/SOURCES.txt
jcore_api.egg-info/dependency_links.txt
jcore_api.egg-info/not-zip-safe
jcore_api.egg-info/requires.txt
jcore_api.egg-info/top_level.txt
jcore_api/_unix_sockets/__init__.py
jcore_api/_unix_sockets/_jcore_unix_socket.py
jcore_api/_unix_sockets/_message_codec.py