Metadata-Version: 1.0
Name: jcore-api
Version: 1.0.1
Summary: jcore.io API
Home-page: http://github.com/jcoreio/jcore-api-py
Author: Andy Edwards
Author-email: andy@jcore.io
License: MIT
Platform: UNKNOWN
